topsis/__init__.py
topsis/__main__.py
Topsis_RashmeetKaur_102017065-0.0.0.dist-info/LICENSE
Topsis_RashmeetKaur_102017065-0.0.0.dist-info/METADATA
Topsis_RashmeetKaur_102017065-0.0.0.dist-info/WHEEL
Topsis_RashmeetKaur_102017065-0.0.0.dist-info/entry_points.txt
Topsis_RashmeetKaur_102017065-0.0.0.dist-info/top_level.txt
Topsis_RashmeetKaur_102017065-0.0.0.dist-info/RECORD
