Metadata-Version: 2.1
Name: Topsis-RashmeetKaur-102017065
Version: 0.0.0
Summary: Topsis Implementation
Home-page: https://github.com/Rashmeet1-hub/Topsis-RashmeetKaur-102017065.git
Author: Rashmeet Kaur
Author-email: rkaur1_be20@thapar.edu
License: MIT
Classifier: License :: OSI Approved :: MIT License
Classifier: Programming Language :: Python :: 3.6
Classifier: Programming Language :: Python :: 3.7
Classifier: Programming Language :: Python :: 3.8
License-File: LICENSE
